<?xml version="1.0" encoding="utf-8"?>
<!DOCTYPE hibernate-mapping PUBLIC "-//Hibernate/Hibernate Mapping DTD 3.0//EN"
"http://hibernate.sourceforge.net/hibernate-mapping-3.0.dtd">
<!-- 
    Mapping file autogenerated by MyEclipse Persistence Tools
-->
<hibernate-mapping>
    <class name="com.web.model.SysLog" table="SYS_LOG" schema="csdb">
        <id name="id" type="java.lang.Long">
            <column name="ID" precision="18" scale="0" />
            <generator class="sequence"><param name="sequence">OAPSEQUENCE</param></generator>
        </id>
        <many-to-one name="sysUser" class="com.web.model.SysUser" fetch="select">
            <column name="SYS_USER" precision="18" scale="0" not-null="true" />
        </many-to-one>
        <property name="logDate" type="java.util.Date">
            <column name="LOG_DATE" length="7" not-null="true" />
        </property>
        <property name="sourceType" type="java.lang.Long">
            <column name="SOURCE_TYPE" precision="2" scale="0">
                <comment>1：系统操作 2：数据导入（如：excel） 3：数据导出 4：备份恢复等系统操作</comment>
            </column>
        </property>
        <property name="sourceEvent" type="java.lang.String">
            <column name="SOURCE_EVENT" length="200" not-null="true" />
        </property>
        <property name="operateContent" type="java.lang.String">
            <column name="OPERATE_CONTENT" length="4000" not-null="true" />
        </property>
        <property name="operateResout" type="java.lang.Long">
            <column name="OPERATE_RESOUT" precision="1" scale="0">
                <comment>1:成功 2:失败</comment>
            </column>
        </property>
        <property name="failReason" type="java.lang.String">
            <column name="FAIL_REASON" length="4000" />
        </property>
        <property name="deleteDate" type="java.util.Date">
            <column name="DELETE_DATE" length="7" />
        </property>
        <property name="name" type="java.lang.String">
            <column name="NAME" length="100" />
        </property>
        <property name="isValid" type="java.lang.Long">
            <column name="IS_VALID" precision="1" scale="0" />
        </property>
        <property name="orderby" type="java.lang.Long">
            <column name="ORDERBY" precision="8" scale="0" />
        </property>
        <property name="remark" type="java.lang.String">
            <column name="REMARK" length="200" />
        </property>
        <property name="attr1" type="java.lang.String">
            <column name="ATTR1" length="200" />
        </property>
        <property name="attr2" type="java.lang.String">
            <column name="ATTR2" length="200" />
        </property>
        <property name="attr3" type="java.lang.String">
            <column name="ATTR3" length="200" />
        </property>
    </class>
</hibernate-mapping>
